<map height='48' width='64'>
  <background>
    <layer name='forest1' speed='2'/>
    <layer name='forest2' speed='4'/>
  </background>
  <entities>
    <entity id='0' x='67' y='528'/>
    <entity id='1' x='430' y='736'/>
  </entities>
  <tiles>
    <tile id='3' x='54' y='22'/>
    <tile id='3' x='55' y='22'/>
    <tile id='34' x='56' y='22'/>
    <tile id='35' x='57' y='22'/>
    <tile id='3' x='58' y='22'/>
    <tile id='3' x='59' y='22'/>
    <tile id='66' x='56' y='23'/>
    <tile id='67' x='57' y='23'/>
    <tile id='3' x='32' y='25'/>
    <tile id='3' x='33' y='25'/>
    <tile id='34' x='34' y='25'/>
    <tile id='35' x='35' y='25'/>
    <tile id='3' x='36' y='25'/>
    <tile id='3' x='37' y='25'/>
    <tile id='66' x='34' y='26'/>
    <tile id='67' x='35' y='26'/>
    <tile id='34' x='13' y='29'/>
    <tile id='35' x='14' y='29'/>
    <tile id='3' x='15' y='29'/>
    <tile id='3' x='16' y='29'/>
    <tile id='3' x='17' y='29'/>
    <tile id='34' x='18' y='29'/>
    <tile id='35' x='19' y='29'/>
    <tile id='3' x='20' y='29'/>
    <tile id='3' x='21' y='29'/>
    <tile id='3' x='22' y='29'/>
    <tile id='3' x='23' y='29'/>
    <tile id='3' x='24' y='29'/>
    <tile id='34' x='25' y='29'/>
    <tile id='35' x='26' y='29'/>
    <tile id='66' x='13' y='30'/>
    <tile id='67' x='14' y='30'/>
    <tile id='66' x='18' y='30'/>
    <tile id='67' x='19' y='30'/>
    <tile id='66' x='25' y='30'/>
    <tile id='67' x='26' y='30'/>
    <tile id='32' x='0' y='34'/>
    <tile id='33' x='1' y='34'/>
    <tile id='32' x='2' y='34'/>
    <tile id='33' x='3' y='34'/>
    <tile id='32' x='4' y='34'/>
    <tile id='33' x='5' y='34'/>
    <tile id='32' x='6' y='34'/>
    <tile id='33' x='7' y='34'/>
    <tile id='64' x='0' y='35'/>
    <tile id='65' x='1' y='35'/>
    <tile id='64' x='2' y='35'/>
    <tile id='65' x='3' y='35'/>
    <tile id='64' x='4' y='35'/>
    <tile id='65' x='5' y='35'/>
    <tile id='64' x='6' y='35'/>
    <tile id='65' x='7' y='35'/>
    <tile id='32' x='13' y='39'/>
    <tile id='33' x='14' y='39'/>
    <tile id='2' x='15' y='39'/>
    <tile id='2' x='22' y='39'/>
    <tile id='32' x='23' y='39'/>
    <tile id='33' x='24' y='39'/>
    <tile id='32' x='25' y='39'/>
    <tile id='33' x='26' y='39'/>
    <tile id='32' x='27' y='39'/>
    <tile id='33' x='28' y='39'/>
    <tile id='64' x='13' y='40'/>
    <tile id='65' x='14' y='40'/>
    <tile id='64' x='23' y='40'/>
    <tile id='65' x='24' y='40'/>
    <tile id='64' x='25' y='40'/>
    <tile id='65' x='26' y='40'/>
    <tile id='64' x='27' y='40'/>
    <tile id='65' x='28' y='40'/>
    <tile id='32' x='12' y='41'/>
    <tile id='33' x='13' y='41'/>
    <tile id='32' x='29' y='41'/>
    <tile id='33' x='30' y='41'/>
    <tile id='64' x='12' y='42'/>
    <tile id='65' x='13' y='42'/>
    <tile id='64' x='29' y='42'/>
    <tile id='65' x='30' y='42'/>
    <tile id='32' x='11' y='43'/>
    <tile id='33' x='12' y='43'/>
    <tile id='64' x='11' y='44'/>
    <tile id='65' x='12' y='44'/>
    <tile id='32' x='10' y='45'/>
    <tile id='33' x='11' y='45'/>
    <tile id='32' x='34' y='45'/>
    <tile id='33' x='35' y='45'/>
    <tile id='64' x='10' y='46'/>
    <tile id='65' x='11' y='46'/>
    <tile id='3' x='22' y='46'/>
    <tile id='64' x='34' y='46'/>
    <tile id='65' x='35' y='46'/>
    <tile id='2' x='0' y='47'/>
    <tile id='2' x='1' y='47'/>
    <tile id='2' x='2' y='47'/>
    <tile id='2' x='3' y='47'/>
    <tile id='2' x='4' y='47'/>
    <tile id='2' x='5' y='47'/>
    <tile id='2' x='6' y='47'/>
    <tile id='2' x='7' y='47'/>
    <tile id='2' x='8' y='47'/>
    <tile id='2' x='9' y='47'/>
    <tile id='2' x='10' y='47'/>
    <tile id='2' x='11' y='47'/>
    <tile id='2' x='12' y='47'/>
    <tile id='2' x='13' y='47'/>
    <tile id='2' x='14' y='47'/>
    <tile id='2' x='15' y='47'/>
    <tile id='2' x='16' y='47'/>
    <tile id='2' x='17' y='47'/>
    <tile id='2' x='18' y='47'/>
    <tile id='2' x='19' y='47'/>
    <tile id='2' x='20' y='47'/>
    <tile id='2' x='21' y='47'/>
    <tile id='2' x='22' y='47'/>
    <tile id='2' x='23' y='47'/>
    <tile id='2' x='24' y='47'/>
    <tile id='2' x='25' y='47'/>
    <tile id='2' x='26' y='47'/>
    <tile id='2' x='27' y='47'/>
    <tile id='2' x='28' y='47'/>
    <tile id='2' x='29' y='47'/>
    <tile id='2' x='30' y='47'/>
    <tile id='2' x='31' y='47'/>
    <tile id='2' x='32' y='47'/>
    <tile id='2' x='33' y='47'/>
    <tile id='2' x='34' y='47'/>
    <tile id='2' x='35' y='47'/>
    <tile id='2' x='36' y='47'/>
    <tile id='2' x='37' y='47'/>
    <tile id='2' x='38' y='47'/>
    <tile id='2' x='39' y='47'/>
    <tile id='2' x='40' y='47'/>
    <tile id='2' x='41' y='47'/>
    <tile id='2' x='42' y='47'/>
    <tile id='2' x='43' y='47'/>
    <tile id='2' x='44' y='47'/>
    <tile id='2' x='45' y='47'/>
    <tile id='2' x='46' y='47'/>
    <tile id='2' x='47' y='47'/>
    <tile id='2' x='48' y='47'/>
    <tile id='2' x='49' y='47'/>
    <tile id='2' x='50' y='47'/>
    <tile id='2' x='51' y='47'/>
    <tile id='2' x='52' y='47'/>
    <tile id='2' x='53' y='47'/>
    <tile id='2' x='54' y='47'/>
    <tile id='2' x='55' y='47'/>
    <tile id='2' x='56' y='47'/>
    <tile id='2' x='57' y='47'/>
    <tile id='2' x='58' y='47'/>
    <tile id='2' x='59' y='47'/>
    <tile id='2' x='60' y='47'/>
    <tile id='2' x='61' y='47'/>
    <tile id='2' x='62' y='47'/>
    <tile id='2' x='63' y='47'/>
  </tiles>
</map>

